mastermind/__init__.py
mastermind/game/__init__.py
mastermind/game/board.py
mastermind/game/game.py
mastermind/game/game_flow.py
mastermind/game/game_parameter.py
mastermind/game/player_logic.py
mastermind/main/__init__.py
mastermind/main/game_controller.py
mastermind/main/game_history.py
mastermind/main/game_storage.py
mastermind/main/main.py
mastermind/players/__init__.py
mastermind/players/abstract_player.py
mastermind/players/ai_player.py
mastermind/players/external_player.py
mastermind/players/human_player.py
mastermind/storage/__init__.py
mastermind/storage/persistent_cache.py
mastermind/storage/user_data.py
mastermind/ui/__init__.py
mastermind/ui/menu/__init__.py
mastermind/ui/menu/base_menu.py
mastermind/ui/menu/concrete_menus.py
mastermind/ui/menu/data_menu.py
mastermind/ui/menu/option_menu.py
mastermind/utils/__init__.py
mastermind/utils/fstring_template.py
mastermind/utils/get_feedback.py
mastermind/utils/render_dataframe.py
mastermind/utils/stack.py
mastermind/validation/__init__.py
mastermind/validation/base/__init__.py
mastermind/validation/base/base.py
mastermind/validation/base/exceptions.py
mastermind/validation/base/numeric.py
mastermind/validation/base/semi_mutable.py
mastermind/validation/base/validated_class.py
mastermind/validation/models/__init__.py
mastermind/validation/models/_game_utils.py
mastermind/validation/models/numeric.py
mastermind/validation/models/valid_combination.py
mastermind/validation/models/valid_feedback.py
mastermind_ai-1.6.2b0.dist-info/LICENSE
mastermind_ai-1.6.2b0.dist-info/METADATA
mastermind_ai-1.6.2b0.dist-info/WHEEL
mastermind_ai-1.6.2b0.dist-info/entry_points.txt
mastermind_ai-1.6.2b0.dist-info/top_level.txt
mastermind_ai-1.6.2b0.dist-info/RECORD
