Metadata-Version: 2.1
Name: mastermind-ai
Version: 1.6.2b0
Summary: A Python package that simulates the Mastermind game with an AI solver.
Home-page: https://github.com/FlysonBot/Mastermind
Author: FlysonBot
Author-email: FlysonBot@users.noreply.github.com
Project-URL: Repository, https://github.com/FlysonBot/Mastermind
Project-URL: Documentation, https://flysonbot.github.io/Mastermind/
Project-URL: Issues and Bugs, https://github.com/FlysonBot/Mastermind/issues
Classifier: Development Status :: 4 - Beta
Classifier: Programming Language :: Python :: 3.10
Classifier: License :: OSI Approved :: MIT License
Classifier: Intended Audience :: End Users/Desktop
Classifier: Intended Audience :: Education
Classifier: Natural Language :: English
Classifier: Topic :: Games/Entertainment :: Puzzle Games
Classifier: Operating System :: OS Independent
Requires-Python: >=3.10
License-File: LICENSE
Requires-Dist: pandas>=2.2.2
